Workbook

Sheet Start here
B2: Beer365 Readiness Workbook
B3: What to gather before a Beer365 assessment, and a first look at what your brewery could save.
B5: How to use it | C5: Fill the yellow cells only. Everything else is a formula and updates as you type. Grey italic rows are examples showing the expected format; overwrite or delete them.
B6: 1 Brewery profile | C6: Volumes, costs and the assumptions every other sheet uses. Ten minutes.
B7: 2 Records | C7: Where each record your brewery keeps actually lives, and how much you trust it. This is the biggest single predictor of how fast Beer365 goes live.
B8: 3 Meters | C8: The measurement points the savings depend on, and when each was last calibrated.
B9: 4 Baseline | C9: Up to twelve months of plant figures. Loss, brewhouse yield, energy and water ratios are worked out for you.
B10: 5 Savings | C10: The five savings formulas from beer365 (beer loss, extract, energy, dumped batches, reporting), fed by your own numbers. Planning figures, not a promise: the real starting point is measured and signed in the assessment.
B11: 6 Questions | C11: All 221 questions Beer365 answers. Score how much each matters and whether you have the data; the priority column ranks them.
B12: 7 Readiness | C12: One page summary: records, meters, baseline coverage and an overall readiness score.
B13: When you are done | C13: Send the workbook to info@disruptive-advantage.com, or bring it to the first call. We read it before we meet.
B14: Colour legend | C14: Yellow fill and blue text: your input. Black text: a formula. Do not overwrite formulas.
B15: Your data | C15: Nothing in this file leaves your hands unless you send it. It contains no macros and no links.
B17: Beer365, built by Disruptive Advantage. ankurnapa.github.io/disruptive-advantage

Sheet 1 Profile
A1: Brewery profile
A2: Yellow cells are yours. The example column shows the expected format.
A4: Item | B4: Your brewery | C4: Example | D4: Why we ask | E4: Used in the sheets
A5: Brewery name | C5: Example Brewing Co | E5: =IF(B5="",C5,B5) -> Example Brewing Co
A6: Currency used below | C6: INR | D6: Every money figure in this workbook is in this currency. | E6: =IF(B6="",C6,B6) -> INR
A7: Beer packaged a year (hL) | C7: 120000 | D7: Drives every saving. | E7: =IF(B7="",C7,B7) -> 120000
A8: Brews a week | C8: 18 | E8: =IF(B8="",C8,B8) -> 18
A9: Number of fermenters and unitanks | C9: 15 | E9: =IF(B9="",C9,B9) -> 15
A10: Packaging lines (bottle, can, keg) | C10: 3 | E10: =IF(B10="",C10,B10) -> 3
A11: Malt and adjunct charged a year (kg) | C11: 2100000 | D11: Base for extract and brewhouse yield. | E11: =IF(B11="",C11,B11) -> 2100000
A12: Malt and adjunct cost per kg | C12: 45 | D12: Hypothetical example price. | E12: =IF(B12="",C12,B12) -> 45
A13: Average extract of the grist, as-is (%) | C13: 0.78 | D13: From the malt certificates; fine grind, as-is basis. | E13: =IF(B13="",C13,B13) -> 0.78
A14: Brewing cost per hL (malt, hops, energy, water) | C14: 2000 | D14: Lost beer is valued at cost to make, not selling price. | E14: =IF(B14="",C14,B14) -> 2000
A15: Energy cost per hL (power plus steam) | C15: 200 | D15: Or leave blank and use the Baseline sheet. | E15: =IF(B15="",C15,B15) -> 200
A16: Brewhouse efficiency today (%) | C16: 0.92 | D16: If you know it. The Baseline sheet also works it out. | E16: =IF(B16="",C16,B16) -> 0.92
A17: Hours a week spent compiling reports by hand | C17: 20 | D17: All people, all reports. | E17: =IF(B17="",C17,B17) -> 20
A18: Cost of an hour of that time | C18: 600 | D18: Loaded cost. | E18: =IF(B18="",C18,B18) -> 600
A19: Main ERP or accounting system | C19: Excel | E19: =IF(B19="",C19,B19) -> Excel
A20: Process historian or SCADA | C20: None | E20: =IF(B20="",C20,B20) -> None
A21: Laboratory system (LIMS) or lab sheets | C21: Excel lab sheets | E21: =IF(B21="",C21,B21) -> Excel lab sheets
A22: Cloud you already use (Azure, AWS, Google, none) | C22: Microsoft 365 only | D22: Beer365 runs in your own Azure tenant; it can read data held on AWS or Google. | E22: =IF(B22="",C22,B22) -> Microsoft 365 only
A24: Until you fill a yellow cell, the sheets use the example value beside it, so the savings page shows a worked example from the start.

Sheet 2 Records
A1: Where your records live
A2: One row per record. Choose where it is kept, how often it is updated, and how much you trust it (1 low to 5 high).
A4: Area | B4: Record | C4: Where it is kept | D4: How often | E4: Owner | F4: Trust 1 to 5 | G4: Ready score | H4: Notes
A5: Raw materials and recipe | B5: Malt certificates of analysis by lot | C5: Excel or Google Sheets | D5: Each batch | E5: Quality manager | F5: 4 | G5: =IF(C5="","",IF(C5="Not kept",0,IF(F5="",0.5,F5/5)*IF(C5="Paper",0.5,1))) -> 0.8 | H5: Example row: overwrite with your own
A6: Raw materials and recipe | B6: Hop certificates and alpha acid by lot | G6: =IF(C6="","",IF(C6="Not kept",0,IF(F6="",0.5,F6/5)*IF(C6="Paper",0.5,1)))
A7: Raw materials and recipe | B7: Water analysis | G7: =IF(C7="","",IF(C7="Not kept",0,IF(F7="",0.5,F7/5)*IF(C7="Paper",0.5,1)))
A8: Raw materials and recipe | B8: Goods received and lot numbers | G8: =IF(C8="","",IF(C8="Not kept",0,IF(F8="",0.5,F8/5)*IF(C8="Paper",0.5,1)))
A9: Raw materials and recipe | B9: Recipes and specifications | G9: =IF(C9="","",IF(C9="Not kept",0,IF(F9="",0.5,F9/5)*IF(C9="Paper",0.5,1)))
A10: Brewhouse | B10: Brew sheets (grist, volumes, gravities, times) | G10: =IF(C10="","",IF(C10="Not kept",0,IF(F10="",0.5,F10/5)*IF(C10="Paper",0.5,1)))
A11: Brewhouse | B11: Mash and kettle temperature logs | G11: =IF(C11="","",IF(C11="Not kept",0,IF(F11="",0.5,F11/5)*IF(C11="Paper",0.5,1)))
A12: Brewhouse | B12: Wort volumes at kettle and knockout | G12: =IF(C12="","",IF(C12="Not kept",0,IF(F12="",0.5,F12/5)*IF(C12="Paper",0.5,1)))
A13: Fermentation and cellar | B13: Fermentation gravity and temperature readings | G13: =IF(C13="","",IF(C13="Not kept",0,IF(F13="",0.5,F13/5)*IF(C13="Paper",0.5,1)))
A14: Fermentation and cellar | B14: Yeast pitch, generation and viability | G14: =IF(C14="","",IF(C14="Not kept",0,IF(F14="",0.5,F14/5)*IF(C14="Paper",0.5,1)))
A15: Fermentation and cellar | B15: Tank transfers and losses | G15: =IF(C15="","",IF(C15="Not kept",0,IF(F15="",0.5,F15/5)*IF(C15="Paper",0.5,1)))
A16: Fermentation and cellar | B16: Filtration and bright beer tank records | G16: =IF(C16="","",IF(C16="Not kept",0,IF(F16="",0.5,F16/5)*IF(C16="Paper",0.5,1)))
A17: Packaging | B17: Line counts, rejects and downtime | G17: =IF(C17="","",IF(C17="Not kept",0,IF(F17="",0.5,F17/5)*IF(C17="Paper",0.5,1)))
... A38: Finance, duty, ESG and people | B38: Monthly management reports | G38: =IF(C38="","",IF(C38="Not kept",0,IF(F38="",0.5,F38/5)*IF(C38="Paper",0.5,1)))
A40: Ready score: 0 if not kept; trust out of 5, halved for paper records because they have to be keyed in first.

Sheet 3 Meters
A1: Meters and instruments
A2: Is it fitted, and when was it last calibrated? Savings are only as good as the meter behind them.
A4: Measurement point | B4: Fitted? | C4: Last calibrated | D4: Within 12 months | E4: Notes
A5: Malt intake weigher or silo load cells | B5: Yes | C5: 46023 | D5: =IF(C5="",IF(B5="No","Not fitted",""),IF(TODAY()-C5<=365,"Yes","Overdue")) -> Yes | E5: Example row: overwrite with your own
A6: Hot liquor and sparge water flow | D6: =IF(C6="",IF(B6="No","Not fitted",""),IF(TODAY()-C6<=365,"Yes","Overdue"))
A7: Wort flow or volume at knockout | D7: =IF(C7="",IF(B7="No","Not fitted",""),IF(TODAY()-C7<=365,"Yes","Overdue"))
A8: Wort gravity at knockout (density meter or lab) | D8: =IF(C8="",IF(B8="No","Not fitted",""),IF(TODAY()-C8<=365,"Yes","Overdue"))
A9: Fermenter level or volume | D9: =IF(C9="",IF(B9="No","Not fitted",""),IF(TODAY()-C9<=365,"Yes","Overdue"))
A10: Fermenter temperature probes | D10: =IF(C10="",IF(B10="No","Not fitted",""),IF(TODAY()-C10<=365,"Yes","Overdue"))
A11: Inline gravity in fermentation (if fitted) | D11: =IF(C11="",IF(B11="No","Not fitted",""),IF(TODAY()-C11<=365,"Yes","Overdue"))
A12: Bright beer tank level | D12: =IF(C12="",IF(B12="No","Not fitted",""),IF(TODAY()-C12<=365,"Yes","Overdue"))
A13: Dissolved oxygen meter (packaging) | D13: =IF(C13="",IF(B13="No","Not fitted",""),IF(TODAY()-C13<=365,"Yes","Overdue"))
A14: Filler counters and rejects | D14: =IF(C14="",IF(B14="No","Not fitted",""),IF(TODAY()-C14<=365,"Yes","Overdue"))
A15: Keg fill weight scale | D15: =IF(C15="",IF(B15="No","Not fitted",""),IF(TODAY()-C15<=365,"Yes","Overdue"))
A16: Main power meter | D16: =IF(C16="",IF(B16="No","Not fitted",""),IF(TODAY()-C16<=365,"Yes","Overdue"))
A17: Power meters by area | D17: =IF(C17="",IF(B17="No","Not fitted",""),IF(TODAY()-C17<=365,"Yes","Overdue"))
... A22: Refrigeration plant power | D22: =IF(C22="",IF(B22="No","Not fitted",""),IF(TODAY()-C22<=365,"Yes","Overdue"))

Sheet 4 Baseline
A1: Baseline months
A2: Up to twelve months of plant figures. Yellow columns are yours; the grey columns are worked out. One example month is filled in.
A4: Month | B4: Brews | C4: Grist charged (kg) | D4: Knockout wort (hL) | E4: Knockout gravity (°P) | F4: Beer to bright tank (hL) | G4: Beer packaged (hL) | H4: Dumped (hL) | I4: Power (kWh) | J4: Steam or fuel (MJ) | K4: Water (hL) | L4: Brewhouse yield | M4: Wort to pack loss | N4: kWh per hL | O4: MJ per hL | P4: Water to beer (hL/hL)
A5: 46143 | B5: 78 | C5: 191000 | D5: 10900 | E5: 12 | F5: 10400 | G5: 10000 | H5: 20 | I5: 95000 | J5: 1200000 | K5: 42000 | L5: =IF(OR(C5="",D5="",E5=""),"",IFERROR((D5*100*(1+E5/(258.6-E5/258.2*227.1))*E5/100)/(C5*'1 Profile'!$E$13),"")) -> 0.92044485 | M5: =IF(OR(D5="",G5=""),"",1-G5/D5) -> 0.082568807 | N5: =IF(OR(I5="",G5="",G5=0),"",I5/G5) -> 9.5 | O5: =IF(OR(J5="",G5="",G5=0),"",J5/G5) -> 120 | P5: =IF(OR(K5="",G5="",G5=0),"",K5/G5) -> 4.2
L6: =IF(OR(C6="",D6="",E6=""),"",IFERROR((D6*100*(1+E6/(258.6-E6/258.2*227.1))*E6/100)/(C6*'1 Profile'!$E$13),"")) | M6: =IF(OR(D6="",G6=""),"",1-G6/D6) | N6: =IF(OR(I6="",G6="",G6=0),"",I6/G6) | O6: =IF(OR(J6="",G6="",G6=0),"",J6/G6) | P6: =IF(OR(K6="",G6="",G6=0),"",K6/G6)
L7: =IF(OR(C7="",D7="",E7=""),"",IFERROR((D7*100*(1+E7/(258.6-E7/258.2*227.1))*E7/100)/(C7*'1 Profile'!$E$13),"")) | M7: =IF(OR(D7="",G7=""),"",1-G7/D7) | N7: =IF(OR(I7="",G7="",G7=0),"",I7/G7) | O7: =IF(OR(J7="",G7="",G7=0),"",J7/G7) | P7: =IF(OR(K7="",G7="",G7=0),"",K7/G7)
L8: =IF(OR(C8="",D8="",E8=""),"",IFERROR((D8*100*(1+E8/(258.6-E8/258.2*227.1))*E8/100)/(C8*'1 Profile'!$E$13),"")) | M8: =IF(OR(D8="",G8=""),"",1-G8/D8) | N8: =IF(OR(I8="",G8="",G8=0),"",I8/G8) | O8: =IF(OR(J8="",G8="",G8=0),"",J8/G8) | P8: =IF(OR(K8="",G8="",G8=0),"",K8/G8)
L9: =IF(OR(C9="",D9="",E9=""),"",IFERROR((D9*100*(1+E9/(258.6-E9/258.2*227.1))*E9/100)/(C9*'1 Profile'!$E$13),"")) | M9: =IF(OR(D9="",G9=""),"",1-G9/D9) | N9: =IF(OR(I9="",G9="",G9=0),"",I9/G9) | O9: =IF(OR(J9="",G9="",G9=0),"",J9/G9) | P9: =IF(OR(K9="",G9="",G9=0),"",K9/G9)
L10: =IF(OR(C10="",D10="",E10=""),"",IFERROR((D10*100*(1+E10/(258.6-E10/258.2*227.1))*E10/100)/(C10*'1 Profile'!$E$13),"")) | M10: =IF(OR(D10="",G10=""),"",1-G10/D10) | N10: =IF(OR(I10="",G10="",G10=0),"",I10/G10) | O10: =IF(OR(J10="",G10="",G10=0),"",J10/G10) | P10: =IF(OR(K10="",G10="",G10=0),"",K10/G10)
L11: =IF(OR(C11="",D11="",E11=""),"",IFERROR((D11*100*(1+E11/(258.6-E11/258.2*227.1))*E11/100)/(C11*'1 Profile'!$E$13),"")) | M11: =IF(OR(D11="",G11=""),"",1-G11/D11) | N11: =IF(OR(I11="",G11="",G11=0),"",I11/G11) | O11: =IF(OR(J11="",G11="",G11=0),"",J11/G11) | P11: =IF(OR(K11="",G11="",G11=0),"",K11/G11)
L12: =IF(OR(C12="",D12="",E12=""),"",IFERROR((D12*100*(1+E12/(258.6-E12/258.2*227.1))*E12/100)/(C12*'1 Profile'!$E$13),"")) | M12: =IF(OR(D12="",G12=""),"",1-G12/D12) | N12: =IF(OR(I12="",G12="",G12=0),"",I12/G12) | O12: =IF(OR(J12="",G12="",G12=0),"",J12/G12) | P12: =IF(OR(K12="",G12="",G12=0),"",K12/G12)
L13: =IF(OR(C13="",D13="",E13=""),"",IFERROR((D13*100*(1+E13/(258.6-E13/258.2*227.1))*E13/100)/(C13*'1 Profile'!$E$13),"")) | M13: =IF(OR(D13="",G13=""),"",1-G13/D13) | N13: =IF(OR(I13="",G13="",G13=0),"",I13/G13) | O13: =IF(OR(J13="",G13="",G13=0),"",J13/G13) | P13: =IF(OR(K13="",G13="",G13=0),"",K13/G13)
L14: =IF(OR(C14="",D14="",E14=""),"",IFERROR((D14*100*(1+E14/(258.6-E14/258.2*227.1))*E14/100)/(C14*'1 Profile'!$E$13),"")) | M14: =IF(OR(D14="",G14=""),"",1-G14/D14) | N14: =IF(OR(I14="",G14="",G14=0),"",I14/G14) | O14: =IF(OR(J14="",G14="",G14=0),"",J14/G14) | P14: =IF(OR(K14="",G14="",G14=0),"",K14/G14)
L15: =IF(OR(C15="",D15="",E15=""),"",IFERROR((D15*100*(1+E15/(258.6-E15/258.2*227.1))*E15/100)/(C15*'1 Profile'!$E$13),"")) | M15: =IF(OR(D15="",G15=""),"",1-G15/D15) | N15: =IF(OR(I15="",G15="",G15=0),"",I15/G15) | O15: =IF(OR(J15="",G15="",G15=0),"",J15/G15) | P15: =IF(OR(K15="",G15="",G15=0),"",K15/G15)
L16: =IF(OR(C16="",D16="",E16=""),"",IFERROR((D16*100*(1+E16/(258.6-E16/258.2*227.1))*E16/100)/(C16*'1 Profile'!$E$13),"")) | M16: =IF(OR(D16="",G16=""),"",1-G16/D16) | N16: =IF(OR(I16="",G16="",G16=0),"",I16/G16) | O16: =IF(OR(J16="",G16="",G16=0),"",J16/G16) | P16: =IF(OR(K16="",G16="",G16=0),"",K16/G16)
A17: Average | B17: =IFERROR(AVERAGE(B5:B16),"") -> 78 | C17: =IFERROR(AVERAGE(C5:C16),"") -> 191000 | D17: =IFERROR(AVERAGE(D5:D16),"") -> 10900 | E17: =IFERROR(AVERAGE(E5:E16),"") -> 12 | F17: =IFERROR(AVERAGE(F5:F16),"") -> 10400 | G17: =IFERROR(AVERAGE(G5:G16),"") -> 10000 | H17: =IFERROR(AVERAGE(H5:H16),"") -> 20 | I17: =IFERROR(AVERAGE(I5:I16),"") -> 95000 | ... P17: =IFERROR(AVERAGE(P5:P16),"") -> 4.2
A19: Brewhouse yield = extract in knockout wort (kg) / extract charged (kg). Extract in wort = litres x SG x °P / 100, with SG from °P by the ASBC approximation SG = 1 + P / (258.6 - (P / 258.2) x 227.1). Charged extract = grist kg x average extract as-is from the Profile sheet. Wort to pack loss compares packaged beer with knockout wort volume; it includes trub, yeast, filtration and packaging losses.

Sheet 5 Savings
A1: What it could be worth
A2: The five formulas Beer365 uses, fed by your figures. Change any yellow assumption to your own view.
A4: Assumption | B4: Value | C4: Basis
A5: Points of beer loss recovered | B5: 0.01 | C5: Breweries without a stage view commonly lose several percent between brewhouse and pack; we assume one point.
A6: Points of brewhouse efficiency gained | B6: 0.01 | C6: Comparing every brew with the malt's lab value typically moves efficiency by a point or more.
A7: Share of energy saved | B7: 0.05 | C7: Tracking power and steam by area against your best day typically trims a few percent.
A8: Share of volume no longer dumped | B8: 0.002 | C8: Catching fermentation drift early saves the occasional batch.
A9: Share of manual reporting time automated | B9: 0.75 | C9: Daily, weekly and month-end packs built from the record instead of by hand.
A11: Saving | B11: A year | C11: Formula
A12: Beer loss | B12: =IFERROR('1 Profile'!$E$7*$B$5*'1 Profile'!$E$14,0) -> 2400000 | C12: hL a year x points of loss recovered x brewing cost per hL
A13: Extract | B13: =IFERROR(('1 Profile'!$E$11*'1 Profile'!$E$12)*$B$6/IF('1 Profile'!$E$16="",IFERROR('4 Baseline'!L17,0.9),'1 Profile'!$E$16),0) -> 1027173.9 | C13: malt spend a year x points gained / efficiency today
A14: Energy | B14: =IFERROR('1 Profile'!$E$7*'1 Profile'!$E$15*$B$7,0) -> 1200000 | C14: hL a year x energy cost per hL x share saved
A15: Dumped batches | B15: =IFERROR('1 Profile'!$E$7*$B$8*'1 Profile'!$E$14,0) -> 480000 | C15: hL a year x share no longer dumped x brewing cost per hL
A16: Reporting | B16: =IFERROR(('1 Profile'!$E$17*52*'1 Profile'!$E$18)*$B$9,0) -> 468000 | C16: hours a week x 52 x cost per hour x share automated
A17: Total a year | B17: =SUM(B12:B16) -> 5575173.9
A18: Year one (half, while the system goes live) | B18: =B17/2 -> 2787587
A19: Three years | B19: =B17*2.5 -> 13937935
A21: A planning figure from your own inputs, not a promise. We do not count lost sales in sold-out months, faster complaint answers, smaller recalls, water, or packaging on beer no longer lost. In the assessment the real starting point is measured from your records and signed by your plant controller; only savings counted against that baseline are ever claimed.

Sheet 6 Questions
A1: The 221 questions
A2: Score each: how much it matters to you (0 to 3) and whether you have the data today (0 to 3). Priority = matters x data.
A4: ID | B4: Area | C4: Question | D4: Use case | E4: Build wave | F4: Matters 0 to 3 | G4: Data 0 to 3 | H4: Priority
A5: 1 | B5: Raw materials and recipe | C5: Did this malt lot cost me extract? | D5: Malt lot to brewhouse performance | E5: First wave | F5: 3 | G5: 2 | H5: =IF(OR(F5="",G5=""),"",F5*G5) -> 6
A6: 2 | B6: Raw materials and recipe | C6: Is the supplier's certificate telling the truth? | D6: COA versus reality | E6: First wave | H6: =IF(OR(F6="",G6=""),"",F6*G6)
A7: 3 | B7: Raw materials and recipe | C7: What bitterness am I actually buying by the time I use it? | D7: Hop alpha decay tracking | E7: First wave | H7: =IF(OR(F7="",G7=""),"",F7*G7)
A8: 4 | B8: Raw materials and recipe | C8: Which supplier is quietly the expensive one? | D8: Supplier scorecard by lot | E8: First wave | H8: =IF(OR(F8="",G8=""),"",F8*G8)
A9: 5 | B9: Raw materials and recipe | C9: Am I over contracted on a hop I no longer sell? | D9: Contract and purchase timing | E9: First wave | H9: =IF(OR(F9="",G9=""),"",F9*G9)
A10: 6 | B10: Raw materials and recipe | C10: Can rice or syrup replace malt without breaking spec? | D10: Adjunct substitution feasibility | E10: First wave | H10: =IF(OR(F10="",G10=""),"",F10*G10)
A11: 7 | B11: Raw materials and recipe | C11: Has my liquor changed under me this season? | D11: Water source seasonal shift | E11: Second wave | H11: =IF(OR(F11="",G11=""),"",F11*G11)
A12: 8 | B12: Raw materials and recipe | C12: Do these cans or crowns leak more than the last lot? | D12: Packaging material lot to defect | E12: Second wave | H12: =IF(OR(F12="",G12=""),"",F12*G12)
A13: 9 | B13: Raw materials and recipe | C13: What is sitting in goods-in that I cannot use? | D13: Quarantine and expiry exposure | E13: Second wave | H13: =IF(OR(F13="",G13=""),"",F13*G13)
A14: 10 | B14: Raw materials and recipe | C14: What does a hectolitre cost me before I even brew it? | D14: Landed raw material cost per hL | E14: First wave | H14: =IF(OR(F14="",G14=""),"",F14*G14)
A15: 11 | B15: Raw materials and recipe | C15: Will the 200 L trial behave the same at 200 hL? | D15: Pilot to production scale up | E15: Second wave | H15: =IF(OR(F15="",G15=""),"",F15*G15)
A16: 12 | B16: Raw materials and recipe | C16: What does this beer cost me today, not last quarter? | D16: Live cost to brew per recipe | E16: First wave | H16: =IF(OR(F16="",G16=""),"",F16*G16)
A17: 13 | B17: Raw materials and recipe | C17: Can I hit the same spec for less money? | D17: Least cost reformulation | E17: First wave | H17: =IF(OR(F17="",G17=""),"",F17*G17)
... A225: 221 | B225: Packaging | C225: Did the coldest pack in the tunnel get enough? | D225: PU distribution across the pack | E225: Second wave | H225: =IF(OR(F225="",G225=""),"",F225*G225)

Sheet 7 Readiness
A1: Readiness summary
A2: Worked out from the other sheets. Nothing to fill in here.
A4: Measure | B4: Result | C4: What it means
A5: Records listed | B5: =COUNTA('2 Records'!B5:B38) -> 34
A6: Records you have answered | B6: =COUNTA('2 Records'!C5:C38) -> 1
A7: Records kept somewhere | B7: =COUNTA('2 Records'!C5:C38)-COUNTIF('2 Records'!C5:C38,"Not kept") -> 1
A8: Records on paper | B8: =COUNTIF('2 Records'!C5:C38,"Paper") -> 0 | C8: Paper records are fine; they are keyed in during the first two weeks.
A9: Records score | B9: =IFERROR(AVERAGE('2 Records'!G5:G38),0) -> 0.8 | C9: Average ready score of the records you answered.
A10: Meters fitted | B10: =COUNTIF('3 Meters'!B5:B22,"Yes") -> 1
A11: Meters calibrated in the last 12 months | B11: =COUNTIF('3 Meters'!D5:D22,"Yes") -> 1
A12: Meters score | B12: =IFERROR(B11/B10,0) -> 1 | C12: Share of fitted meters that are in calibration.
A13: Baseline months entered | B13: =COUNT('4 Baseline'!G5:G16) -> 1 | C13: Three months is enough to start; twelve shows seasonality.
A14: Baseline score | B14: =MIN(1,B13/3) -> 0.33333333
A15: Questions scored | B15: =COUNT('6 Questions'!H5:H225) -> 1
A16: Questions with priority 6 or more | B16: =COUNTIF('6 Questions'!H5:H225,">=6") -> 1 | C16: These are where the first modules should start.
A17: Planning saving a year | B17: ='5 Savings'!B17 -> 5575173.9 | C17: In the currency on the Profile sheet.
A18: Overall readiness | B18: =ROUND(0.5*B9+0.2*B12+0.3*B14,2) -> 0.7 | C18: Half records, a fifth meters, the rest baseline.
A19: Verdict | B19: =IF(B18>=0.7,"Ready to start",IF(B18>=0.4,"Ready with a two-week data tidy-up","Start with the records")) -> Ready to start
